{"eventCount":39,"events":["ES_EVENT_TYPE_AUTH_OPEN","ES_EVENT_TYPE_AUTH_MMAP","ES_EVENT_TYPE_AUTH_MPROTECT","ES_EVENT_TYPE_AUTH_RENAME","ES_EVENT_TYPE_AUTH_SIGNAL","ES_EVENT_TYPE_AUTH_UNLINK","ES_EVENT_TYPE_AUTH_READLINK","ES_EVENT_TYPE_AUTH_TRUNCATE","ES_EVENT_TYPE_AUTH_LINK","ES_EVENT_TYPE_AUTH_CREATE","ES_EVENT_TYPE_AUTH_SETATTRLIST","ES_EVENT_TYPE_AUTH_SETEXTATTR","ES_EVENT_TYPE_AUTH_SETFLAGS","ES_EVENT_TYPE_AUTH_SETMODE","ES_EVENT_TYPE_AUTH_SETOWNER","ES_EVENT_TYPE_AUTH_CHDIR","ES_EVENT_TYPE_AUTH_GETATTRLIST","ES_EVENT_TYPE_AUTH_CHROOT","ES_EVENT_TYPE_AUTH_UTIMES","ES_EVENT_TYPE_AUTH_CLONE","ES_EVENT_TYPE_AUTH_GETEXTATTR","ES_EVENT_TYPE_AUTH_LISTEXTATTR","ES_EVENT_TYPE_AUTH_READDIR","ES_EVENT_TYPE_AUTH_DELETEEXTATTR","ES_EVENT_TYPE_AUTH_FSGETPATH","ES_EVENT_TYPE_AUTH_SETTIME","ES_EVENT_TYPE_AUTH_UIPC_BIND","ES_EVENT_TYPE_AUTH_UIPC_CONNECT","ES_EVENT_TYPE_AUTH_EXCHANGEDATA","ES_EVENT_TYPE_AUTH_SETACL","ES_EVENT_TYPE_AUTH_PROC_CHECK","ES_EVENT_TYPE_AUTH_GET_TASK","ES_EVENT_TYPE_AUTH_SEARCHFS","ES_EVENT_TYPE_AUTH_FCNTL","ES_EVENT_TYPE_AUTH_IOKIT_OPEN","ES_EVENT_TYPE_AUTH_PROC_SUSPEND_RESUME","ES_EVENT_TYPE_AUTH_REMOUNT","ES_EVENT_TYPE_AUTH_GET_TASK_READ","ES_EVENT_TYPE_AUTH_COPYFILE"],"path":"/System/Library/Frameworks/CoreTelephony.framework/Support/CommCenter","type":"ES_MUTE_PATH_TYPE_LITERAL"}
{"eventCount":1,"events":["ES_EVENT_TYPE_AUTH_EXEC"],"path":"/usr/sbin/spindump","type":"ES_MUTE_PATH_TYPE_TARGET_LITERAL"}
{"eventCount":39,"events":["ES_EVENT_TYPE_AUTH_OPEN","ES_EVENT_TYPE_AUTH_MMAP","ES_EVENT_TYPE_AUTH_MPROTECT","ES_EVENT_TYPE_AUTH_RENAME","ES_EVENT_TYPE_AUTH_SIGNAL","ES_EVENT_TYPE_AUTH_UNLINK","ES_EVENT_TYPE_AUTH_READLINK","ES_EVENT_TYPE_AUTH_TRUNCATE","ES_EVENT_TYPE_AUTH_LINK","ES_EVENT_TYPE_AUTH_CREATE","ES_EVENT_TYPE_AUTH_SETATTRLIST","ES_EVENT_TYPE_AUTH_SETEXTATTR","ES_EVENT_TYPE_AUTH_SETFLAGS","ES_EVENT_TYPE_AUTH_SETMODE","ES_EVENT_TYPE_AUTH_SETOWNER","ES_EVENT_TYPE_AUTH_CHDIR","ES_EVENT_TYPE_AUTH_GETATTRLIST","ES_EVENT_TYPE_AUTH_CHROOT","ES_EVENT_TYPE_AUTH_UTIMES","ES_EVENT_TYPE_AUTH_CLONE","ES_EVENT_TYPE_AUTH_GETEXTATTR","ES_EVENT_TYPE_AUTH_LISTEXTATTR","ES_EVENT_TYPE_AUTH_READDIR","ES_EVENT_TYPE_AUTH_DELETEEXTATTR","ES_EVENT_TYPE_AUTH_FSGETPATH","ES_EVENT_TYPE_AUTH_SETTIME","ES_EVENT_TYPE_AUTH_UIPC_BIND","ES_EVENT_TYPE_AUTH_UIPC_CONNECT","ES_EVENT_TYPE_AUTH_EXCHANGEDATA","ES_EVENT_TYPE_AUTH_SETACL","ES_EVENT_TYPE_AUTH_PROC_CHECK","ES_EVENT_TYPE_AUTH_GET_TASK","ES_EVENT_TYPE_AUTH_SEARCHFS","ES_EVENT_TYPE_AUTH_FCNTL","ES_EVENT_TYPE_AUTH_IOKIT_OPEN","ES_EVENT_TYPE_AUTH_PROC_SUSPEND_RESUME","ES_EVENT_TYPE_AUTH_REMOUNT","ES_EVENT_TYPE_AUTH_GET_TASK_READ","ES_EVENT_TYPE_AUTH_COPYFILE"],"path":"/usr/sbin/securityd","type":"ES_MUTE_PATH_TYPE_LITERAL"}
{"eventCount":39,"events":["ES_EVENT_TYPE_AUTH_OPEN","ES_EVENT_TYPE_AUTH_MMAP","ES_EVENT_TYPE_AUTH_MPROTECT","ES_EVENT_TYPE_AUTH_RENAME","ES_EVENT_TYPE_AUTH_SIGNAL","ES_EVENT_TYPE_AUTH_UNLINK","ES_EVENT_TYPE_AUTH_READLINK","ES_EVENT_TYPE_AUTH_TRUNCATE","ES_EVENT_TYPE_AUTH_LINK","ES_EVENT_TYPE_AUTH_CREATE","ES_EVENT_TYPE_AUTH_SETATTRLIST","ES_EVENT_TYPE_AUTH_SETEXTATTR","ES_EVENT_TYPE_AUTH_SETFLAGS","ES_EVENT_TYPE_AUTH_SETMODE","ES_EVENT_TYPE_AUTH_SETOWNER","ES_EVENT_TYPE_AUTH_CHDIR","ES_EVENT_TYPE_AUTH_GETATTRLIST","ES_EVENT_TYPE_AUTH_CHROOT","ES_EVENT_TYPE_AUTH_UTIMES","ES_EVENT_TYPE_AUTH_CLONE","ES_EVENT_TYPE_AUTH_GETEXTATTR","ES_EVENT_TYPE_AUTH_LISTEXTATTR","ES_EVENT_TYPE_AUTH_READDIR","ES_EVENT_TYPE_AUTH_DELETEEXTATTR","ES_EVENT_TYPE_AUTH_FSGETPATH","ES_EVENT_TYPE_AUTH_SETTIME","ES_EVENT_TYPE_AUTH_UIPC_BIND","ES_EVENT_TYPE_AUTH_UIPC_CONNECT","ES_EVENT_TYPE_AUTH_EXCHANGEDATA","ES_EVENT_TYPE_AUTH_SETACL","ES_EVENT_TYPE_AUTH_PROC_CHECK","ES_EVENT_TYPE_AUTH_GET_TASK","ES_EVENT_TYPE_AUTH_SEARCHFS","ES_EVENT_TYPE_AUTH_FCNTL","ES_EVENT_TYPE_AUTH_IOKIT_OPEN","ES_EVENT_TYPE_AUTH_PROC_SUSPEND_RESUME","ES_EVENT_TYPE_AUTH_REMOUNT","ES_EVENT_TYPE_AUTH_GET_TASK_READ","ES_EVENT_TYPE_AUTH_COPYFILE"],"path":"/usr/bin/tailspin","type":"ES_MUTE_PATH_TYPE_LITERAL"}
{"eventCount":39,"events":["ES_EVENT_TYPE_AUTH_OPEN","ES_EVENT_TYPE_AUTH_MMAP","ES_EVENT_TYPE_AUTH_MPROTECT","ES_EVENT_TYPE_AUTH_RENAME","ES_EVENT_TYPE_AUTH_SIGNAL","ES_EVENT_TYPE_AUTH_UNLINK","ES_EVENT_TYPE_AUTH_READLINK","ES_EVENT_TYPE_AUTH_TRUNCATE","ES_EVENT_TYPE_AUTH_LINK","ES_EVENT_TYPE_AUTH_CREATE","ES_EVENT_TYPE_AUTH_SETATTRLIST","ES_EVENT_TYPE_AUTH_SETEXTATTR","ES_EVENT_TYPE_AUTH_SETFLAGS","ES_EVENT_TYPE_AUTH_SETMODE","ES_EVENT_TYPE_AUTH_SETOWNER","ES_EVENT_TYPE_AUTH_CHDIR","ES_EVENT_TYPE_AUTH_GETATTRLIST","ES_EVENT_TYPE_AUTH_CHROOT","ES_EVENT_TYPE_AUTH_UTIMES","ES_EVENT_TYPE_AUTH_CLONE","ES_EVENT_TYPE_AUTH_GETEXTATTR","ES_EVENT_TYPE_AUTH_LISTEXTATTR","ES_EVENT_TYPE_AUTH_READDIR","ES_EVENT_TYPE_AUTH_DELETEEXTATTR","ES_EVENT_TYPE_AUTH_FSGETPATH","ES_EVENT_TYPE_AUTH_SETTIME","ES_EVENT_TYPE_AUTH_UIPC_BIND","ES_EVENT_TYPE_AUTH_UIPC_CONNECT","ES_EVENT_TYPE_AUTH_EXCHANGEDATA","ES_EVENT_TYPE_AUTH_SETACL","ES_EVENT_TYPE_AUTH_PROC_CHECK","ES_EVENT_TYPE_AUTH_GET_TASK","ES_EVENT_TYPE_AUTH_SEARCHFS","ES_EVENT_TYPE_AUTH_FCNTL","ES_EVENT_TYPE_AUTH_IOKIT_OPEN","ES_EVENT_TYPE_AUTH_PROC_SUSPEND_RESUME","ES_EVENT_TYPE_AUTH_REMOUNT","ES_EVENT_TYPE_AUTH_GET_TASK_READ","ES_EVENT_TYPE_AUTH_COPYFILE"],"path":"/usr/libexec/amfid","type":"ES_MUTE_PATH_TYPE_LITERAL"}
{"eventCount":38,"events":["ES_EVENT_TYPE_AUTH_OPEN","ES_EVENT_TYPE_AUTH_MMAP","ES_EVENT_TYPE_AUTH_MPROTECT","ES_EVENT_TYPE_AUTH_RENAME","ES_EVENT_TYPE_AUTH_SIGNAL","ES_EVENT_TYPE_AUTH_UNLINK","ES_EVENT_TYPE_AUTH_READLINK","ES_EVENT_TYPE_AUTH_TRUNCATE","ES_EVENT_TYPE_AUTH_LINK","ES_EVENT_TYPE_AUTH_CREATE","ES_EVENT_TYPE_AUTH_SETATTRLIST","ES_EVENT_TYPE_AUTH_SETEXTATTR","ES_EVENT_TYPE_AUTH_SETFLAGS","ES_EVENT_TYPE_AUTH_SETMODE","ES_EVENT_TYPE_AUTH_SETOWNER","ES_EVENT_TYPE_AUTH_CHDIR","ES_EVENT_TYPE_AUTH_GETATTRLIST","ES_EVENT_TYPE_AUTH_CHROOT","ES_EVENT_TYPE_AUTH_UTIMES","ES_EVENT_TYPE_AUTH_CLONE","ES_EVENT_TYPE_AUTH_GETEXTATTR","ES_EVENT_TYPE_AUTH_LISTEXTATTR","ES_EVENT_TYPE_AUTH_READDIR","ES_EVENT_TYPE_AUTH_DELETEEXTATTR","ES_EVENT_TYPE_AUTH_FSGETPATH","ES_EVENT_TYPE_AUTH_SETTIME","ES_EVENT_TYPE_AUTH_UIPC_BIND","ES_EVENT_TYPE_AUTH_UIPC_CONNECT","ES_EVENT_TYPE_AUTH_EXCHANGEDATA","ES_EVENT_TYPE_AUTH_SETACL","ES_EVENT_TYPE_AUTH_PROC_CHECK","ES_EVENT_TYPE_AUTH_GET_TASK","ES_EVENT_TYPE_AUTH_SEARCHFS","ES_EVENT_TYPE_AUTH_FCNTL","ES_EVENT_TYPE_AUTH_IOKIT_OPEN","ES_EVENT_TYPE_AUTH_PROC_SUSPEND_RESUME","ES_EVENT_TYPE_AUTH_REMOUNT","ES_EVENT_TYPE_AUTH_GET_TASK_READ"],"path":"/usr/libexec/logd","type":"ES_MUTE_PATH_TYPE_LITERAL"}
{"eventCount":39,"events":["ES_EVENT_TYPE_AUTH_OPEN","ES_EVENT_TYPE_AUTH_MMAP","ES_EVENT_TYPE_AUTH_MPROTECT","ES_EVENT_TYPE_AUTH_RENAME","ES_EVENT_TYPE_AUTH_SIGNAL","ES_EVENT_TYPE_AUTH_UNLINK","ES_EVENT_TYPE_AUTH_READLINK","ES_EVENT_TYPE_AUTH_TRUNCATE","ES_EVENT_TYPE_AUTH_LINK","ES_EVENT_TYPE_AUTH_CREATE","ES_EVENT_TYPE_AUTH_SETATTRLIST","ES_EVENT_TYPE_AUTH_SETEXTATTR","ES_EVENT_TYPE_AUTH_SETFLAGS","ES_EVENT_TYPE_AUTH_SETMODE","ES_EVENT_TYPE_AUTH_SETOWNER","ES_EVENT_TYPE_AUTH_CHDIR","ES_EVENT_TYPE_AUTH_GETATTRLIST","ES_EVENT_TYPE_AUTH_CHROOT","ES_EVENT_TYPE_AUTH_UTIMES","ES_EVENT_TYPE_AUTH_CLONE","ES_EVENT_TYPE_AUTH_GETEXTATTR","ES_EVENT_TYPE_AUTH_LISTEXTATTR","ES_EVENT_TYPE_AUTH_READDIR","ES_EVENT_TYPE_AUTH_DELETEEXTATTR","ES_EVENT_TYPE_AUTH_FSGETPATH","ES_EVENT_TYPE_AUTH_SETTIME","ES_EVENT_TYPE_AUTH_UIPC_BIND","ES_EVENT_TYPE_AUTH_UIPC_CONNECT","ES_EVENT_TYPE_AUTH_EXCHANGEDATA","ES_EVENT_TYPE_AUTH_SETACL","ES_EVENT_TYPE_AUTH_PROC_CHECK","ES_EVENT_TYPE_AUTH_GET_TASK","ES_EVENT_TYPE_AUTH_SEARCHFS","ES_EVENT_TYPE_AUTH_FCNTL","ES_EVENT_TYPE_AUTH_IOKIT_OPEN","ES_EVENT_TYPE_AUTH_PROC_SUSPEND_RESUME","ES_EVENT_TYPE_AUTH_REMOUNT","ES_EVENT_TYPE_AUTH_GET_TASK_READ","ES_EVENT_TYPE_AUTH_COPYFILE"],"path":"/usr/libexec/configd","type":"ES_MUTE_PATH_TYPE_LITERAL"}
{"eventCount":39,"events":["ES_EVENT_TYPE_AUTH_OPEN","ES_EVENT_TYPE_AUTH_MMAP","ES_EVENT_TYPE_AUTH_MPROTECT","ES_EVENT_TYPE_AUTH_RENAME","ES_EVENT_TYPE_AUTH_SIGNAL","ES_EVENT_TYPE_AUTH_UNLINK","ES_EVENT_TYPE_AUTH_READLINK","ES_EVENT_TYPE_AUTH_TRUNCATE","ES_EVENT_TYPE_AUTH_LINK","ES_EVENT_TYPE_AUTH_CREATE","ES_EVENT_TYPE_AUTH_SETATTRLIST","ES_EVENT_TYPE_AUTH_SETEXTATTR","ES_EVENT_TYPE_AUTH_SETFLAGS","ES_EVENT_TYPE_AUTH_SETMODE","ES_EVENT_TYPE_AUTH_SETOWNER","ES_EVENT_TYPE_AUTH_CHDIR","ES_EVENT_TYPE_AUTH_GETATTRLIST","ES_EVENT_TYPE_AUTH_CHROOT","ES_EVENT_TYPE_AUTH_UTIMES","ES_EVENT_TYPE_AUTH_CLONE","ES_EVENT_TYPE_AUTH_GETEXTATTR","ES_EVENT_TYPE_AUTH_LISTEXTATTR","ES_EVENT_TYPE_AUTH_READDIR","ES_EVENT_TYPE_AUTH_DELETEEXTATTR","ES_EVENT_TYPE_AUTH_FSGETPATH","ES_EVENT_TYPE_AUTH_SETTIME","ES_EVENT_TYPE_AUTH_UIPC_BIND","ES_EVENT_TYPE_AUTH_UIPC_CONNECT","ES_EVENT_TYPE_AUTH_EXCHANGEDATA","ES_EVENT_TYPE_AUTH_SETACL","ES_EVENT_TYPE_AUTH_PROC_CHECK","ES_EVENT_TYPE_AUTH_GET_TASK","ES_EVENT_TYPE_AUTH_SEARCHFS","ES_EVENT_TYPE_AUTH_FCNTL","ES_EVENT_TYPE_AUTH_IOKIT_OPEN","ES_EVENT_TYPE_AUTH_PROC_SUSPEND_RESUME","ES_EVENT_TYPE_AUTH_REMOUNT","ES_EVENT_TYPE_AUTH_GET_TASK_READ","ES_EVENT_TYPE_AUTH_COPYFILE"],"path":"/usr/libexec/lightsoutmanagementd","type":"ES_MUTE_PATH_TYPE_LITERAL"}
{"eventCount":1,"events":["ES_EVENT_TYPE_AUTH_EXEC"],"path":"/usr/bin/lskq","type":"ES_MUTE_PATH_TYPE_TARGET_LITERAL"}
{"eventCount":39,"events":["ES_EVENT_TYPE_AUTH_OPEN","ES_EVENT_TYPE_AUTH_MMAP","ES_EVENT_TYPE_AUTH_MPROTECT","ES_EVENT_TYPE_AUTH_RENAME","ES_EVENT_TYPE_AUTH_SIGNAL","ES_EVENT_TYPE_AUTH_UNLINK","ES_EVENT_TYPE_AUTH_READLINK","ES_EVENT_TYPE_AUTH_TRUNCATE","ES_EVENT_TYPE_AUTH_LINK","ES_EVENT_TYPE_AUTH_CREATE","ES_EVENT_TYPE_AUTH_SETATTRLIST","ES_EVENT_TYPE_AUTH_SETEXTATTR","ES_EVENT_TYPE_AUTH_SETFLAGS","ES_EVENT_TYPE_AUTH_SETMODE","ES_EVENT_TYPE_AUTH_SETOWNER","ES_EVENT_TYPE_AUTH_CHDIR","ES_EVENT_TYPE_AUTH_GETATTRLIST","ES_EVENT_TYPE_AUTH_CHROOT","ES_EVENT_TYPE_AUTH_UTIMES","ES_EVENT_TYPE_AUTH_CLONE","ES_EVENT_TYPE_AUTH_GETEXTATTR","ES_EVENT_TYPE_AUTH_LISTEXTATTR","ES_EVENT_TYPE_AUTH_READDIR","ES_EVENT_TYPE_AUTH_DELETEEXTATTR","ES_EVENT_TYPE_AUTH_FSGETPATH","ES_EVENT_TYPE_AUTH_SETTIME","ES_EVENT_TYPE_AUTH_UIPC_BIND","ES_EVENT_TYPE_AUTH_UIPC_CONNECT","ES_EVENT_TYPE_AUTH_EXCHANGEDATA","ES_EVENT_TYPE_AUTH_SETACL","ES_EVENT_TYPE_AUTH_PROC_CHECK","ES_EVENT_TYPE_AUTH_GET_TASK","ES_EVENT_TYPE_AUTH_SEARCHFS","ES_EVENT_TYPE_AUTH_FCNTL","ES_EVENT_TYPE_AUTH_IOKIT_OPEN","ES_EVENT_TYPE_AUTH_PROC_SUSPEND_RESUME","ES_EVENT_TYPE_AUTH_REMOUNT","ES_EVENT_TYPE_AUTH_GET_TASK_READ","ES_EVENT_TYPE_AUTH_COPYFILE"],"path":"/usr/bin/lskq","type":"ES_MUTE_PATH_TYPE_LITERAL"}
{"eventCount":39,"events":["ES_EVENT_TYPE_AUTH_OPEN","ES_EVENT_TYPE_AUTH_MMAP","ES_EVENT_TYPE_AUTH_MPROTECT","ES_EVENT_TYPE_AUTH_RENAME","ES_EVENT_TYPE_AUTH_SIGNAL","ES_EVENT_TYPE_AUTH_UNLINK","ES_EVENT_TYPE_AUTH_READLINK","ES_EVENT_TYPE_AUTH_TRUNCATE","ES_EVENT_TYPE_AUTH_LINK","ES_EVENT_TYPE_AUTH_CREATE","ES_EVENT_TYPE_AUTH_SETATTRLIST","ES_EVENT_TYPE_AUTH_SETEXTATTR","ES_EVENT_TYPE_AUTH_SETFLAGS","ES_EVENT_TYPE_AUTH_SETMODE","ES_EVENT_TYPE_AUTH_SETOWNER","ES_EVENT_TYPE_AUTH_CHDIR","ES_EVENT_TYPE_AUTH_GETATTRLIST","ES_EVENT_TYPE_AUTH_CHROOT","ES_EVENT_TYPE_AUTH_UTIMES","ES_EVENT_TYPE_AUTH_CLONE","ES_EVENT_TYPE_AUTH_GETEXTATTR","ES_EVENT_TYPE_AUTH_LISTEXTATTR","ES_EVENT_TYPE_AUTH_READDIR","ES_EVENT_TYPE_AUTH_DELETEEXTATTR","ES_EVENT_TYPE_AUTH_FSGETPATH","ES_EVENT_TYPE_AUTH_SETTIME","ES_EVENT_TYPE_AUTH_UIPC_BIND","ES_EVENT_TYPE_AUTH_UIPC_CONNECT","ES_EVENT_TYPE_AUTH_EXCHANGEDATA","ES_EVENT_TYPE_AUTH_SETACL","ES_EVENT_TYPE_AUTH_PROC_CHECK","ES_EVENT_TYPE_AUTH_GET_TASK","ES_EVENT_TYPE_AUTH_SEARCHFS","ES_EVENT_TYPE_AUTH_FCNTL","ES_EVENT_TYPE_AUTH_IOKIT_OPEN","ES_EVENT_TYPE_AUTH_PROC_SUSPEND_RESUME","ES_EVENT_TYPE_AUTH_REMOUNT","ES_EVENT_TYPE_AUTH_GET_TASK_READ","ES_EVENT_TYPE_AUTH_COPYFILE"],"path":"/System/Library/PrivateFrameworks/TCC.framework/Support/tccd","type":"ES_MUTE_PATH_TYPE_LITERAL"}
{"eventCount":39,"events":["ES_EVENT_TYPE_AUTH_OPEN","ES_EVENT_TYPE_AUTH_MMAP","ES_EVENT_TYPE_AUTH_MPROTECT","ES_EVENT_TYPE_AUTH_RENAME","ES_EVENT_TYPE_AUTH_SIGNAL","ES_EVENT_TYPE_AUTH_UNLINK","ES_EVENT_TYPE_AUTH_READLINK","ES_EVENT_TYPE_AUTH_TRUNCATE","ES_EVENT_TYPE_AUTH_LINK","ES_EVENT_TYPE_AUTH_CREATE","ES_EVENT_TYPE_AUTH_SETATTRLIST","ES_EVENT_TYPE_AUTH_SETEXTATTR","ES_EVENT_TYPE_AUTH_SETFLAGS","ES_EVENT_TYPE_AUTH_SETMODE","ES_EVENT_TYPE_AUTH_SETOWNER","ES_EVENT_TYPE_AUTH_CHDIR","ES_EVENT_TYPE_AUTH_GETATTRLIST","ES_EVENT_TYPE_AUTH_CHROOT","ES_EVENT_TYPE_AUTH_UTIMES","ES_EVENT_TYPE_AUTH_CLONE","ES_EVENT_TYPE_AUTH_GETEXTATTR","ES_EVENT_TYPE_AUTH_LISTEXTATTR","ES_EVENT_TYPE_AUTH_READDIR","ES_EVENT_TYPE_AUTH_DELETEEXTATTR","ES_EVENT_TYPE_AUTH_FSGETPATH","ES_EVENT_TYPE_AUTH_SETTIME","ES_EVENT_TYPE_AUTH_UIPC_BIND","ES_EVENT_TYPE_AUTH_UIPC_CONNECT","ES_EVENT_TYPE_AUTH_EXCHANGEDATA","ES_EVENT_TYPE_AUTH_SETACL","ES_EVENT_TYPE_AUTH_PROC_CHECK","ES_EVENT_TYPE_AUTH_GET_TASK","ES_EVENT_TYPE_AUTH_SEARCHFS","ES_EVENT_TYPE_AUTH_FCNTL","ES_EVENT_TYPE_AUTH_IOKIT_OPEN","ES_EVENT_TYPE_AUTH_PROC_SUSPEND_RESUME","ES_EVENT_TYPE_AUTH_REMOUNT","ES_EVENT_TYPE_AUTH_GET_TASK_READ","ES_EVENT_TYPE_AUTH_COPYFILE"],"path":"/usr/bin/heap","type":"ES_MUTE_PATH_TYPE_LITERAL"}
{"eventCount":39,"events":["ES_EVENT_TYPE_AUTH_OPEN","ES_EVENT_TYPE_AUTH_MMAP","ES_EVENT_TYPE_AUTH_MPROTECT","ES_EVENT_TYPE_AUTH_RENAME","ES_EVENT_TYPE_AUTH_SIGNAL","ES_EVENT_TYPE_AUTH_UNLINK","ES_EVENT_TYPE_AUTH_READLINK","ES_EVENT_TYPE_AUTH_TRUNCATE","ES_EVENT_TYPE_AUTH_LINK","ES_EVENT_TYPE_AUTH_CREATE","ES_EVENT_TYPE_AUTH_SETATTRLIST","ES_EVENT_TYPE_AUTH_SETEXTATTR","ES_EVENT_TYPE_AUTH_SETFLAGS","ES_EVENT_TYPE_AUTH_SETMODE","ES_EVENT_TYPE_AUTH_SETOWNER","ES_EVENT_TYPE_AUTH_CHDIR","ES_EVENT_TYPE_AUTH_GETATTRLIST","ES_EVENT_TYPE_AUTH_CHROOT","ES_EVENT_TYPE_AUTH_UTIMES","ES_EVENT_TYPE_AUTH_CLONE","ES_EVENT_TYPE_AUTH_GETEXTATTR","ES_EVENT_TYPE_AUTH_LISTEXTATTR","ES_EVENT_TYPE_AUTH_READDIR","ES_EVENT_TYPE_AUTH_DELETEEXTATTR","ES_EVENT_TYPE_AUTH_FSGETPATH","ES_EVENT_TYPE_AUTH_SETTIME","ES_EVENT_TYPE_AUTH_UIPC_BIND","ES_EVENT_TYPE_AUTH_UIPC_CONNECT","ES_EVENT_TYPE_AUTH_EXCHANGEDATA","ES_EVENT_TYPE_AUTH_SETACL","ES_EVENT_TYPE_AUTH_PROC_CHECK","ES_EVENT_TYPE_AUTH_GET_TASK","ES_EVENT_TYPE_AUTH_SEARCHFS","ES_EVENT_TYPE_AUTH_FCNTL","ES_EVENT_TYPE_AUTH_IOKIT_OPEN","ES_EVENT_TYPE_AUTH_PROC_SUSPEND_RESUME","ES_EVENT_TYPE_AUTH_REMOUNT","ES_EVENT_TYPE_AUTH_GET_TASK_READ","ES_EVENT_TYPE_AUTH_COPYFILE"],"path":"/usr/libexec/kernelmanagerd","type":"ES_MUTE_PATH_TYPE_LITERAL"}
{"eventCount":1,"events":["ES_EVENT_TYPE_AUTH_EXEC"],"path":"/usr/bin/heap","type":"ES_MUTE_PATH_TYPE_TARGET_LITERAL"}
{"eventCount":39,"events":["ES_EVENT_TYPE_AUTH_OPEN","ES_EVENT_TYPE_AUTH_MMAP","ES_EVENT_TYPE_AUTH_MPROTECT","ES_EVENT_TYPE_AUTH_RENAME","ES_EVENT_TYPE_AUTH_SIGNAL","ES_EVENT_TYPE_AUTH_UNLINK","ES_EVENT_TYPE_AUTH_READLINK","ES_EVENT_TYPE_AUTH_TRUNCATE","ES_EVENT_TYPE_AUTH_LINK","ES_EVENT_TYPE_AUTH_CREATE","ES_EVENT_TYPE_AUTH_SETATTRLIST","ES_EVENT_TYPE_AUTH_SETEXTATTR","ES_EVENT_TYPE_AUTH_SETFLAGS","ES_EVENT_TYPE_AUTH_SETMODE","ES_EVENT_TYPE_AUTH_SETOWNER","ES_EVENT_TYPE_AUTH_CHDIR","ES_EVENT_TYPE_AUTH_GETATTRLIST","ES_EVENT_TYPE_AUTH_CHROOT","ES_EVENT_TYPE_AUTH_UTIMES","ES_EVENT_TYPE_AUTH_CLONE","ES_EVENT_TYPE_AUTH_GETEXTATTR","ES_EVENT_TYPE_AUTH_LISTEXTATTR","ES_EVENT_TYPE_AUTH_READDIR","ES_EVENT_TYPE_AUTH_DELETEEXTATTR","ES_EVENT_TYPE_AUTH_FSGETPATH","ES_EVENT_TYPE_AUTH_SETTIME","ES_EVENT_TYPE_AUTH_UIPC_BIND","ES_EVENT_TYPE_AUTH_UIPC_CONNECT","ES_EVENT_TYPE_AUTH_EXCHANGEDATA","ES_EVENT_TYPE_AUTH_SETACL","ES_EVENT_TYPE_AUTH_PROC_CHECK","ES_EVENT_TYPE_AUTH_GET_TASK","ES_EVENT_TYPE_AUTH_SEARCHFS","ES_EVENT_TYPE_AUTH_FCNTL","ES_EVENT_TYPE_AUTH_IOKIT_OPEN","ES_EVENT_TYPE_AUTH_PROC_SUSPEND_RESUME","ES_EVENT_TYPE_AUTH_REMOUNT","ES_EVENT_TYPE_AUTH_GET_TASK_READ","ES_EVENT_TYPE_AUTH_COPYFILE"],"path":"/usr/local/libexec/automationdevicemonitoringd","type":"ES_MUTE_PATH_TYPE_LITERAL"}
{"eventCount":39,"events":["ES_EVENT_TYPE_AUTH_OPEN","ES_EVENT_TYPE_AUTH_MMAP","ES_EVENT_TYPE_AUTH_MPROTECT","ES_EVENT_TYPE_AUTH_RENAME","ES_EVENT_TYPE_AUTH_SIGNAL","ES_EVENT_TYPE_AUTH_UNLINK","ES_EVENT_TYPE_AUTH_READLINK","ES_EVENT_TYPE_AUTH_TRUNCATE","ES_EVENT_TYPE_AUTH_LINK","ES_EVENT_TYPE_AUTH_CREATE","ES_EVENT_TYPE_AUTH_SETATTRLIST","ES_EVENT_TYPE_AUTH_SETEXTATTR","ES_EVENT_TYPE_AUTH_SETFLAGS","ES_EVENT_TYPE_AUTH_SETMODE","ES_EVENT_TYPE_AUTH_SETOWNER","ES_EVENT_TYPE_AUTH_CHDIR","ES_EVENT_TYPE_AUTH_GETATTRLIST","ES_EVENT_TYPE_AUTH_CHROOT","ES_EVENT_TYPE_AUTH_UTIMES","ES_EVENT_TYPE_AUTH_CLONE","ES_EVENT_TYPE_AUTH_GETEXTATTR","ES_EVENT_TYPE_AUTH_LISTEXTATTR","ES_EVENT_TYPE_AUTH_READDIR","ES_EVENT_TYPE_AUTH_DELETEEXTATTR","ES_EVENT_TYPE_AUTH_FSGETPATH","ES_EVENT_TYPE_AUTH_SETTIME","ES_EVENT_TYPE_AUTH_UIPC_BIND","ES_EVENT_TYPE_AUTH_UIPC_CONNECT","ES_EVENT_TYPE_AUTH_EXCHANGEDATA","ES_EVENT_TYPE_AUTH_SETACL","ES_EVENT_TYPE_AUTH_PROC_CHECK","ES_EVENT_TYPE_AUTH_GET_TASK","ES_EVENT_TYPE_AUTH_SEARCHFS","ES_EVENT_TYPE_AUTH_FCNTL","ES_EVENT_TYPE_AUTH_IOKIT_OPEN","ES_EVENT_TYPE_AUTH_PROC_SUSPEND_RESUME","ES_EVENT_TYPE_AUTH_REMOUNT","ES_EVENT_TYPE_AUTH_GET_TASK_READ","ES_EVENT_TYPE_AUTH_COPYFILE"],"path":"/usr/libexec/trustd","type":"ES_MUTE_PATH_TYPE_LITERAL"}
{"eventCount":39,"events":["ES_EVENT_TYPE_AUTH_OPEN","ES_EVENT_TYPE_AUTH_MMAP","ES_EVENT_TYPE_AUTH_MPROTECT","ES_EVENT_TYPE_AUTH_RENAME","ES_EVENT_TYPE_AUTH_SIGNAL","ES_EVENT_TYPE_AUTH_UNLINK","ES_EVENT_TYPE_AUTH_READLINK","ES_EVENT_TYPE_AUTH_TRUNCATE","ES_EVENT_TYPE_AUTH_LINK","ES_EVENT_TYPE_AUTH_CREATE","ES_EVENT_TYPE_AUTH_SETATTRLIST","ES_EVENT_TYPE_AUTH_SETEXTATTR","ES_EVENT_TYPE_AUTH_SETFLAGS","ES_EVENT_TYPE_AUTH_SETMODE","ES_EVENT_TYPE_AUTH_SETOWNER","ES_EVENT_TYPE_AUTH_CHDIR","ES_EVENT_TYPE_AUTH_GETATTRLIST","ES_EVENT_TYPE_AUTH_CHROOT","ES_EVENT_TYPE_AUTH_UTIMES","ES_EVENT_TYPE_AUTH_CLONE","ES_EVENT_TYPE_AUTH_GETEXTATTR","ES_EVENT_TYPE_AUTH_LISTEXTATTR","ES_EVENT_TYPE_AUTH_READDIR","ES_EVENT_TYPE_AUTH_DELETEEXTATTR","ES_EVENT_TYPE_AUTH_FSGETPATH","ES_EVENT_TYPE_AUTH_SETTIME","ES_EVENT_TYPE_AUTH_UIPC_BIND","ES_EVENT_TYPE_AUTH_UIPC_CONNECT","ES_EVENT_TYPE_AUTH_EXCHANGEDATA","ES_EVENT_TYPE_AUTH_SETACL","ES_EVENT_TYPE_AUTH_PROC_CHECK","ES_EVENT_TYPE_AUTH_GET_TASK","ES_EVENT_TYPE_AUTH_SEARCHFS","ES_EVENT_TYPE_AUTH_FCNTL","ES_EVENT_TYPE_AUTH_IOKIT_OPEN","ES_EVENT_TYPE_AUTH_PROC_SUSPEND_RESUME","ES_EVENT_TYPE_AUTH_REMOUNT","ES_EVENT_TYPE_AUTH_GET_TASK_READ","ES_EVENT_TYPE_AUTH_COPYFILE"],"path":"/System/Library/PrivateFrameworks/TCC.framework/Versions/A/Resources/tccd","type":"ES_MUTE_PATH_TYPE_LITERAL"}
{"eventCount":39,"events":["ES_EVENT_TYPE_AUTH_OPEN","ES_EVENT_TYPE_AUTH_MMAP","ES_EVENT_TYPE_AUTH_MPROTECT","ES_EVENT_TYPE_AUTH_RENAME","ES_EVENT_TYPE_AUTH_SIGNAL","ES_EVENT_TYPE_AUTH_UNLINK","ES_EVENT_TYPE_AUTH_READLINK","ES_EVENT_TYPE_AUTH_TRUNCATE","ES_EVENT_TYPE_AUTH_LINK","ES_EVENT_TYPE_AUTH_CREATE","ES_EVENT_TYPE_AUTH_SETATTRLIST","ES_EVENT_TYPE_AUTH_SETEXTATTR","ES_EVENT_TYPE_AUTH_SETFLAGS","ES_EVENT_TYPE_AUTH_SETMODE","ES_EVENT_TYPE_AUTH_SETOWNER","ES_EVENT_TYPE_AUTH_CHDIR","ES_EVENT_TYPE_AUTH_GETATTRLIST","ES_EVENT_TYPE_AUTH_CHROOT","ES_EVENT_TYPE_AUTH_UTIMES","ES_EVENT_TYPE_AUTH_CLONE","ES_EVENT_TYPE_AUTH_GETEXTATTR","ES_EVENT_TYPE_AUTH_LISTEXTATTR","ES_EVENT_TYPE_AUTH_READDIR","ES_EVENT_TYPE_AUTH_DELETEEXTATTR","ES_EVENT_TYPE_AUTH_FSGETPATH","ES_EVENT_TYPE_AUTH_SETTIME","ES_EVENT_TYPE_AUTH_UIPC_BIND","ES_EVENT_TYPE_AUTH_UIPC_CONNECT","ES_EVENT_TYPE_AUTH_EXCHANGEDATA","ES_EVENT_TYPE_AUTH_SETACL","ES_EVENT_TYPE_AUTH_PROC_CHECK","ES_EVENT_TYPE_AUTH_GET_TASK","ES_EVENT_TYPE_AUTH_SEARCHFS","ES_EVENT_TYPE_AUTH_FCNTL","ES_EVENT_TYPE_AUTH_IOKIT_OPEN","ES_EVENT_TYPE_AUTH_PROC_SUSPEND_RESUME","ES_EVENT_TYPE_AUTH_REMOUNT","ES_EVENT_TYPE_AUTH_GET_TASK_READ","ES_EVENT_TYPE_AUTH_COPYFILE"],"path":"/usr/appleinternal/bin/tailspin","type":"ES_MUTE_PATH_TYPE_LITERAL"}
{"eventCount":39,"events":["ES_EVENT_TYPE_AUTH_OPEN","ES_EVENT_TYPE_AUTH_MMAP","ES_EVENT_TYPE_AUTH_MPROTECT","ES_EVENT_TYPE_AUTH_RENAME","ES_EVENT_TYPE_AUTH_SIGNAL","ES_EVENT_TYPE_AUTH_UNLINK","ES_EVENT_TYPE_AUTH_READLINK","ES_EVENT_TYPE_AUTH_TRUNCATE","ES_EVENT_TYPE_AUTH_LINK","ES_EVENT_TYPE_AUTH_CREATE","ES_EVENT_TYPE_AUTH_SETATTRLIST","ES_EVENT_TYPE_AUTH_SETEXTATTR","ES_EVENT_TYPE_AUTH_SETFLAGS","ES_EVENT_TYPE_AUTH_SETMODE","ES_EVENT_TYPE_AUTH_SETOWNER","ES_EVENT_TYPE_AUTH_CHDIR","ES_EVENT_TYPE_AUTH_GETATTRLIST","ES_EVENT_TYPE_AUTH_CHROOT","ES_EVENT_TYPE_AUTH_UTIMES","ES_EVENT_TYPE_AUTH_CLONE","ES_EVENT_TYPE_AUTH_GETEXTATTR","ES_EVENT_TYPE_AUTH_LISTEXTATTR","ES_EVENT_TYPE_AUTH_READDIR","ES_EVENT_TYPE_AUTH_DELETEEXTATTR","ES_EVENT_TYPE_AUTH_FSGETPATH","ES_EVENT_TYPE_AUTH_SETTIME","ES_EVENT_TYPE_AUTH_UIPC_BIND","ES_EVENT_TYPE_AUTH_UIPC_CONNECT","ES_EVENT_TYPE_AUTH_EXCHANGEDATA","ES_EVENT_TYPE_AUTH_SETACL","ES_EVENT_TYPE_AUTH_PROC_CHECK","ES_EVENT_TYPE_AUTH_GET_TASK","ES_EVENT_TYPE_AUTH_SEARCHFS","ES_EVENT_TYPE_AUTH_FCNTL","ES_EVENT_TYPE_AUTH_IOKIT_OPEN","ES_EVENT_TYPE_AUTH_PROC_SUSPEND_RESUME","ES_EVENT_TYPE_AUTH_REMOUNT","ES_EVENT_TYPE_AUTH_GET_TASK_READ","ES_EVENT_TYPE_AUTH_COPYFILE"],"path":"/usr/sbin/spindump","type":"ES_MUTE_PATH_TYPE_LITERAL"}
{"eventCount":39,"events":["ES_EVENT_TYPE_AUTH_OPEN","ES_EVENT_TYPE_AUTH_MMAP","ES_EVENT_TYPE_AUTH_MPROTECT","ES_EVENT_TYPE_AUTH_RENAME","ES_EVENT_TYPE_AUTH_SIGNAL","ES_EVENT_TYPE_AUTH_UNLINK","ES_EVENT_TYPE_AUTH_READLINK","ES_EVENT_TYPE_AUTH_TRUNCATE","ES_EVENT_TYPE_AUTH_LINK","ES_EVENT_TYPE_AUTH_CREATE","ES_EVENT_TYPE_AUTH_SETATTRLIST","ES_EVENT_TYPE_AUTH_SETEXTATTR","ES_EVENT_TYPE_AUTH_SETFLAGS","ES_EVENT_TYPE_AUTH_SETMODE","ES_EVENT_TYPE_AUTH_SETOWNER","ES_EVENT_TYPE_AUTH_CHDIR","ES_EVENT_TYPE_AUTH_GETATTRLIST","ES_EVENT_TYPE_AUTH_CHROOT","ES_EVENT_TYPE_AUTH_UTIMES","ES_EVENT_TYPE_AUTH_CLONE","ES_EVENT_TYPE_AUTH_GETEXTATTR","ES_EVENT_TYPE_AUTH_LISTEXTATTR","ES_EVENT_TYPE_AUTH_READDIR","ES_EVENT_TYPE_AUTH_DELETEEXTATTR","ES_EVENT_TYPE_AUTH_FSGETPATH","ES_EVENT_TYPE_AUTH_SETTIME","ES_EVENT_TYPE_AUTH_UIPC_BIND","ES_EVENT_TYPE_AUTH_UIPC_CONNECT","ES_EVENT_TYPE_AUTH_EXCHANGEDATA","ES_EVENT_TYPE_AUTH_SETACL","ES_EVENT_TYPE_AUTH_PROC_CHECK","ES_EVENT_TYPE_AUTH_GET_TASK","ES_EVENT_TYPE_AUTH_SEARCHFS","ES_EVENT_TYPE_AUTH_FCNTL","ES_EVENT_TYPE_AUTH_IOKIT_OPEN","ES_EVENT_TYPE_AUTH_PROC_SUSPEND_RESUME","ES_EVENT_TYPE_AUTH_REMOUNT","ES_EVENT_TYPE_AUTH_GET_TASK_READ","ES_EVENT_TYPE_AUTH_COPYFILE"],"path":"/usr/libexec/opendirectoryd","type":"ES_MUTE_PATH_TYPE_LITERAL"}
{"eventCount":38,"events":["ES_EVENT_TYPE_AUTH_OPEN","ES_EVENT_TYPE_AUTH_MMAP","ES_EVENT_TYPE_AUTH_MPROTECT","ES_EVENT_TYPE_AUTH_RENAME","ES_EVENT_TYPE_AUTH_SIGNAL","ES_EVENT_TYPE_AUTH_UNLINK","ES_EVENT_TYPE_AUTH_READLINK","ES_EVENT_TYPE_AUTH_TRUNCATE","ES_EVENT_TYPE_AUTH_LINK","ES_EVENT_TYPE_AUTH_CREATE","ES_EVENT_TYPE_AUTH_SETATTRLIST","ES_EVENT_TYPE_AUTH_SETEXTATTR","ES_EVENT_TYPE_AUTH_SETFLAGS","ES_EVENT_TYPE_AUTH_SETMODE","ES_EVENT_TYPE_AUTH_SETOWNER","ES_EVENT_TYPE_AUTH_CHDIR","ES_EVENT_TYPE_AUTH_GETATTRLIST","ES_EVENT_TYPE_AUTH_CHROOT","ES_EVENT_TYPE_AUTH_UTIMES","ES_EVENT_TYPE_AUTH_CLONE","ES_EVENT_TYPE_AUTH_GETEXTATTR","ES_EVENT_TYPE_AUTH_LISTEXTATTR","ES_EVENT_TYPE_AUTH_READDIR","ES_EVENT_TYPE_AUTH_DELETEEXTATTR","ES_EVENT_TYPE_AUTH_FSGETPATH","ES_EVENT_TYPE_AUTH_SETTIME","ES_EVENT_TYPE_AUTH_UIPC_BIND","ES_EVENT_TYPE_AUTH_UIPC_CONNECT","ES_EVENT_TYPE_AUTH_EXCHANGEDATA","ES_EVENT_TYPE_AUTH_SETACL","ES_EVENT_TYPE_AUTH_PROC_CHECK","ES_EVENT_TYPE_AUTH_GET_TASK","ES_EVENT_TYPE_AUTH_SEARCHFS","ES_EVENT_TYPE_AUTH_FCNTL","ES_EVENT_TYPE_AUTH_IOKIT_OPEN","ES_EVENT_TYPE_AUTH_PROC_SUSPEND_RESUME","ES_EVENT_TYPE_AUTH_REMOUNT","ES_EVENT_TYPE_AUTH_GET_TASK_READ"],"path":"/System/Library/PrivateFrameworks/SkyLight.framework/Resources/WindowServer","type":"ES_MUTE_PATH_TYPE_LITERAL"}
{"eventCount":1,"events":["ES_EVENT_TYPE_AUTH_EXEC"],"path":"/usr/sbin/lsof","type":"ES_MUTE_PATH_TYPE_TARGET_LITERAL"}
{"eventCount":39,"events":["ES_EVENT_TYPE_AUTH_OPEN","ES_EVENT_TYPE_AUTH_MMAP","ES_EVENT_TYPE_AUTH_MPROTECT","ES_EVENT_TYPE_AUTH_RENAME","ES_EVENT_TYPE_AUTH_SIGNAL","ES_EVENT_TYPE_AUTH_UNLINK","ES_EVENT_TYPE_AUTH_READLINK","ES_EVENT_TYPE_AUTH_TRUNCATE","ES_EVENT_TYPE_AUTH_LINK","ES_EVENT_TYPE_AUTH_CREATE","ES_EVENT_TYPE_AUTH_SETATTRLIST","ES_EVENT_TYPE_AUTH_SETEXTATTR","ES_EVENT_TYPE_AUTH_SETFLAGS","ES_EVENT_TYPE_AUTH_SETMODE","ES_EVENT_TYPE_AUTH_SETOWNER","ES_EVENT_TYPE_AUTH_CHDIR","ES_EVENT_TYPE_AUTH_GETATTRLIST","ES_EVENT_TYPE_AUTH_CHROOT","ES_EVENT_TYPE_AUTH_UTIMES","ES_EVENT_TYPE_AUTH_CLONE","ES_EVENT_TYPE_AUTH_GETEXTATTR","ES_EVENT_TYPE_AUTH_LISTEXTATTR","ES_EVENT_TYPE_AUTH_READDIR","ES_EVENT_TYPE_AUTH_DELETEEXTATTR","ES_EVENT_TYPE_AUTH_FSGETPATH","ES_EVENT_TYPE_AUTH_SETTIME","ES_EVENT_TYPE_AUTH_UIPC_BIND","ES_EVENT_TYPE_AUTH_UIPC_CONNECT","ES_EVENT_TYPE_AUTH_EXCHANGEDATA","ES_EVENT_TYPE_AUTH_SETACL","ES_EVENT_TYPE_AUTH_PROC_CHECK","ES_EVENT_TYPE_AUTH_GET_TASK","ES_EVENT_TYPE_AUTH_SEARCHFS","ES_EVENT_TYPE_AUTH_FCNTL","ES_EVENT_TYPE_AUTH_IOKIT_OPEN","ES_EVENT_TYPE_AUTH_PROC_SUSPEND_RESUME","ES_EVENT_TYPE_AUTH_REMOUNT","ES_EVENT_TYPE_AUTH_GET_TASK_READ","ES_EVENT_TYPE_AUTH_COPYFILE"],"path":"/usr/libexec/sandboxd","type":"ES_MUTE_PATH_TYPE_LITERAL"}
{"eventCount":1,"events":["ES_EVENT_TYPE_AUTH_EXEC"],"path":"/usr/appleinternal/bin/tailspin","type":"ES_MUTE_PATH_TYPE_TARGET_LITERAL"}
{"eventCount":39,"events":["ES_EVENT_TYPE_AUTH_OPEN","ES_EVENT_TYPE_AUTH_MMAP","ES_EVENT_TYPE_AUTH_MPROTECT","ES_EVENT_TYPE_AUTH_RENAME","ES_EVENT_TYPE_AUTH_SIGNAL","ES_EVENT_TYPE_AUTH_UNLINK","ES_EVENT_TYPE_AUTH_READLINK","ES_EVENT_TYPE_AUTH_TRUNCATE","ES_EVENT_TYPE_AUTH_LINK","ES_EVENT_TYPE_AUTH_CREATE","ES_EVENT_TYPE_AUTH_SETATTRLIST","ES_EVENT_TYPE_AUTH_SETEXTATTR","ES_EVENT_TYPE_AUTH_SETFLAGS","ES_EVENT_TYPE_AUTH_SETMODE","ES_EVENT_TYPE_AUTH_SETOWNER","ES_EVENT_TYPE_AUTH_CHDIR","ES_EVENT_TYPE_AUTH_GETATTRLIST","ES_EVENT_TYPE_AUTH_CHROOT","ES_EVENT_TYPE_AUTH_UTIMES","ES_EVENT_TYPE_AUTH_CLONE","ES_EVENT_TYPE_AUTH_GETEXTATTR","ES_EVENT_TYPE_AUTH_LISTEXTATTR","ES_EVENT_TYPE_AUTH_READDIR","ES_EVENT_TYPE_AUTH_DELETEEXTATTR","ES_EVENT_TYPE_AUTH_FSGETPATH","ES_EVENT_TYPE_AUTH_SETTIME","ES_EVENT_TYPE_AUTH_UIPC_BIND","ES_EVENT_TYPE_AUTH_UIPC_CONNECT","ES_EVENT_TYPE_AUTH_EXCHANGEDATA","ES_EVENT_TYPE_AUTH_SETACL","ES_EVENT_TYPE_AUTH_PROC_CHECK","ES_EVENT_TYPE_AUTH_GET_TASK","ES_EVENT_TYPE_AUTH_SEARCHFS","ES_EVENT_TYPE_AUTH_FCNTL","ES_EVENT_TYPE_AUTH_IOKIT_OPEN","ES_EVENT_TYPE_AUTH_PROC_SUSPEND_RESUME","ES_EVENT_TYPE_AUTH_REMOUNT","ES_EVENT_TYPE_AUTH_GET_TASK_READ","ES_EVENT_TYPE_AUTH_COPYFILE"],"path":"/usr/libexec/runningboardd","type":"ES_MUTE_PATH_TYPE_LITERAL"}
{"eventCount":39,"events":["ES_EVENT_TYPE_AUTH_OPEN","ES_EVENT_TYPE_AUTH_MMAP","ES_EVENT_TYPE_AUTH_MPROTECT","ES_EVENT_TYPE_AUTH_RENAME","ES_EVENT_TYPE_AUTH_SIGNAL","ES_EVENT_TYPE_AUTH_UNLINK","ES_EVENT_TYPE_AUTH_READLINK","ES_EVENT_TYPE_AUTH_TRUNCATE","ES_EVENT_TYPE_AUTH_LINK","ES_EVENT_TYPE_AUTH_CREATE","ES_EVENT_TYPE_AUTH_SETATTRLIST","ES_EVENT_TYPE_AUTH_SETEXTATTR","ES_EVENT_TYPE_AUTH_SETFLAGS","ES_EVENT_TYPE_AUTH_SETMODE","ES_EVENT_TYPE_AUTH_SETOWNER","ES_EVENT_TYPE_AUTH_CHDIR","ES_EVENT_TYPE_AUTH_GETATTRLIST","ES_EVENT_TYPE_AUTH_CHROOT","ES_EVENT_TYPE_AUTH_UTIMES","ES_EVENT_TYPE_AUTH_CLONE","ES_EVENT_TYPE_AUTH_GETEXTATTR","ES_EVENT_TYPE_AUTH_LISTEXTATTR","ES_EVENT_TYPE_AUTH_READDIR","ES_EVENT_TYPE_AUTH_DELETEEXTATTR","ES_EVENT_TYPE_AUTH_FSGETPATH","ES_EVENT_TYPE_AUTH_SETTIME","ES_EVENT_TYPE_AUTH_UIPC_BIND","ES_EVENT_TYPE_AUTH_UIPC_CONNECT","ES_EVENT_TYPE_AUTH_EXCHANGEDATA","ES_EVENT_TYPE_AUTH_SETACL","ES_EVENT_TYPE_AUTH_PROC_CHECK","ES_EVENT_TYPE_AUTH_GET_TASK","ES_EVENT_TYPE_AUTH_SEARCHFS","ES_EVENT_TYPE_AUTH_FCNTL","ES_EVENT_TYPE_AUTH_IOKIT_OPEN","ES_EVENT_TYPE_AUTH_PROC_SUSPEND_RESUME","ES_EVENT_TYPE_AUTH_REMOUNT","ES_EVENT_TYPE_AUTH_GET_TASK_READ","ES_EVENT_TYPE_AUTH_COPYFILE"],"path":"/usr/sbin/cfprefsd","type":"ES_MUTE_PATH_TYPE_LITERAL"}
{"eventCount":1,"events":["ES_EVENT_TYPE_AUTH_EXEC"],"path":"/usr/bin/sample","type":"ES_MUTE_PATH_TYPE_TARGET_LITERAL"}
{"eventCount":1,"events":["ES_EVENT_TYPE_AUTH_EXEC"],"path":"/usr/bin/tailspin","type":"ES_MUTE_PATH_TYPE_TARGET_LITERAL"}
{"eventCount":39,"events":["ES_EVENT_TYPE_AUTH_OPEN","ES_EVENT_TYPE_AUTH_MMAP","ES_EVENT_TYPE_AUTH_MPROTECT","ES_EVENT_TYPE_AUTH_RENAME","ES_EVENT_TYPE_AUTH_SIGNAL","ES_EVENT_TYPE_AUTH_UNLINK","ES_EVENT_TYPE_AUTH_READLINK","ES_EVENT_TYPE_AUTH_TRUNCATE","ES_EVENT_TYPE_AUTH_LINK","ES_EVENT_TYPE_AUTH_CREATE","ES_EVENT_TYPE_AUTH_SETATTRLIST","ES_EVENT_TYPE_AUTH_SETEXTATTR","ES_EVENT_TYPE_AUTH_SETFLAGS","ES_EVENT_TYPE_AUTH_SETMODE","ES_EVENT_TYPE_AUTH_SETOWNER","ES_EVENT_TYPE_AUTH_CHDIR","ES_EVENT_TYPE_AUTH_GETATTRLIST","ES_EVENT_TYPE_AUTH_CHROOT","ES_EVENT_TYPE_AUTH_UTIMES","ES_EVENT_TYPE_AUTH_CLONE","ES_EVENT_TYPE_AUTH_GETEXTATTR","ES_EVENT_TYPE_AUTH_LISTEXTATTR","ES_EVENT_TYPE_AUTH_READDIR","ES_EVENT_TYPE_AUTH_DELETEEXTATTR","ES_EVENT_TYPE_AUTH_FSGETPATH","ES_EVENT_TYPE_AUTH_SETTIME","ES_EVENT_TYPE_AUTH_UIPC_BIND","ES_EVENT_TYPE_AUTH_UIPC_CONNECT","ES_EVENT_TYPE_AUTH_EXCHANGEDATA","ES_EVENT_TYPE_AUTH_SETACL","ES_EVENT_TYPE_AUTH_PROC_CHECK","ES_EVENT_TYPE_AUTH_GET_TASK","ES_EVENT_TYPE_AUTH_SEARCHFS","ES_EVENT_TYPE_AUTH_FCNTL","ES_EVENT_TYPE_AUTH_IOKIT_OPEN","ES_EVENT_TYPE_AUTH_PROC_SUSPEND_RESUME","ES_EVENT_TYPE_AUTH_REMOUNT","ES_EVENT_TYPE_AUTH_GET_TASK_READ","ES_EVENT_TYPE_AUTH_COPYFILE"],"path":"/usr/libexec/watchdogd","type":"ES_MUTE_PATH_TYPE_LITERAL"}
{"eventCount":39,"events":["ES_EVENT_TYPE_AUTH_OPEN","ES_EVENT_TYPE_AUTH_MMAP","ES_EVENT_TYPE_AUTH_MPROTECT","ES_EVENT_TYPE_AUTH_RENAME","ES_EVENT_TYPE_AUTH_SIGNAL","ES_EVENT_TYPE_AUTH_UNLINK","ES_EVENT_TYPE_AUTH_READLINK","ES_EVENT_TYPE_AUTH_TRUNCATE","ES_EVENT_TYPE_AUTH_LINK","ES_EVENT_TYPE_AUTH_CREATE","ES_EVENT_TYPE_AUTH_SETATTRLIST","ES_EVENT_TYPE_AUTH_SETEXTATTR","ES_EVENT_TYPE_AUTH_SETFLAGS","ES_EVENT_TYPE_AUTH_SETMODE","ES_EVENT_TYPE_AUTH_SETOWNER","ES_EVENT_TYPE_AUTH_CHDIR","ES_EVENT_TYPE_AUTH_GETATTRLIST","ES_EVENT_TYPE_AUTH_CHROOT","ES_EVENT_TYPE_AUTH_UTIMES","ES_EVENT_TYPE_AUTH_CLONE","ES_EVENT_TYPE_AUTH_GETEXTATTR","ES_EVENT_TYPE_AUTH_LISTEXTATTR","ES_EVENT_TYPE_AUTH_READDIR","ES_EVENT_TYPE_AUTH_DELETEEXTATTR","ES_EVENT_TYPE_AUTH_FSGETPATH","ES_EVENT_TYPE_AUTH_SETTIME","ES_EVENT_TYPE_AUTH_UIPC_BIND","ES_EVENT_TYPE_AUTH_UIPC_CONNECT","ES_EVENT_TYPE_AUTH_EXCHANGEDATA","ES_EVENT_TYPE_AUTH_SETACL","ES_EVENT_TYPE_AUTH_PROC_CHECK","ES_EVENT_TYPE_AUTH_GET_TASK","ES_EVENT_TYPE_AUTH_SEARCHFS","ES_EVENT_TYPE_AUTH_FCNTL","ES_EVENT_TYPE_AUTH_IOKIT_OPEN","ES_EVENT_TYPE_AUTH_PROC_SUSPEND_RESUME","ES_EVENT_TYPE_AUTH_REMOUNT","ES_EVENT_TYPE_AUTH_GET_TASK_READ","ES_EVENT_TYPE_AUTH_COPYFILE"],"path":"/usr/libexec/remoted","type":"ES_MUTE_PATH_TYPE_LITERAL"}
{"eventCount":39,"events":["ES_EVENT_TYPE_AUTH_OPEN","ES_EVENT_TYPE_AUTH_MMAP","ES_EVENT_TYPE_AUTH_MPROTECT","ES_EVENT_TYPE_AUTH_RENAME","ES_EVENT_TYPE_AUTH_SIGNAL","ES_EVENT_TYPE_AUTH_UNLINK","ES_EVENT_TYPE_AUTH_READLINK","ES_EVENT_TYPE_AUTH_TRUNCATE","ES_EVENT_TYPE_AUTH_LINK","ES_EVENT_TYPE_AUTH_CREATE","ES_EVENT_TYPE_AUTH_SETATTRLIST","ES_EVENT_TYPE_AUTH_SETEXTATTR","ES_EVENT_TYPE_AUTH_SETFLAGS","ES_EVENT_TYPE_AUTH_SETMODE","ES_EVENT_TYPE_AUTH_SETOWNER","ES_EVENT_TYPE_AUTH_CHDIR","ES_EVENT_TYPE_AUTH_GETATTRLIST","ES_EVENT_TYPE_AUTH_CHROOT","ES_EVENT_TYPE_AUTH_UTIMES","ES_EVENT_TYPE_AUTH_CLONE","ES_EVENT_TYPE_AUTH_GETEXTATTR","ES_EVENT_TYPE_AUTH_LISTEXTATTR","ES_EVENT_TYPE_AUTH_READDIR","ES_EVENT_TYPE_AUTH_DELETEEXTATTR","ES_EVENT_TYPE_AUTH_FSGETPATH","ES_EVENT_TYPE_AUTH_SETTIME","ES_EVENT_TYPE_AUTH_UIPC_BIND","ES_EVENT_TYPE_AUTH_UIPC_CONNECT","ES_EVENT_TYPE_AUTH_EXCHANGEDATA","ES_EVENT_TYPE_AUTH_SETACL","ES_EVENT_TYPE_AUTH_PROC_CHECK","ES_EVENT_TYPE_AUTH_GET_TASK","ES_EVENT_TYPE_AUTH_SEARCHFS","ES_EVENT_TYPE_AUTH_FCNTL","ES_EVENT_TYPE_AUTH_IOKIT_OPEN","ES_EVENT_TYPE_AUTH_PROC_SUSPEND_RESUME","ES_EVENT_TYPE_AUTH_REMOUNT","ES_EVENT_TYPE_AUTH_GET_TASK_READ","ES_EVENT_TYPE_AUTH_COPYFILE"],"path":"/usr/libexec/syspolicyd","type":"ES_MUTE_PATH_TYPE_LITERAL"}
{"eventCount":39,"events":["ES_EVENT_TYPE_AUTH_OPEN","ES_EVENT_TYPE_AUTH_MMAP","ES_EVENT_TYPE_AUTH_MPROTECT","ES_EVENT_TYPE_AUTH_RENAME","ES_EVENT_TYPE_AUTH_SIGNAL","ES_EVENT_TYPE_AUTH_UNLINK","ES_EVENT_TYPE_AUTH_READLINK","ES_EVENT_TYPE_AUTH_TRUNCATE","ES_EVENT_TYPE_AUTH_LINK","ES_EVENT_TYPE_AUTH_CREATE","ES_EVENT_TYPE_AUTH_SETATTRLIST","ES_EVENT_TYPE_AUTH_SETEXTATTR","ES_EVENT_TYPE_AUTH_SETFLAGS","ES_EVENT_TYPE_AUTH_SETMODE","ES_EVENT_TYPE_AUTH_SETOWNER","ES_EVENT_TYPE_AUTH_CHDIR","ES_EVENT_TYPE_AUTH_GETATTRLIST","ES_EVENT_TYPE_AUTH_CHROOT","ES_EVENT_TYPE_AUTH_UTIMES","ES_EVENT_TYPE_AUTH_CLONE","ES_EVENT_TYPE_AUTH_GETEXTATTR","ES_EVENT_TYPE_AUTH_LISTEXTATTR","ES_EVENT_TYPE_AUTH_READDIR","ES_EVENT_TYPE_AUTH_DELETEEXTATTR","ES_EVENT_TYPE_AUTH_FSGETPATH","ES_EVENT_TYPE_AUTH_SETTIME","ES_EVENT_TYPE_AUTH_UIPC_BIND","ES_EVENT_TYPE_AUTH_UIPC_CONNECT","ES_EVENT_TYPE_AUTH_EXCHANGEDATA","ES_EVENT_TYPE_AUTH_SETACL","ES_EVENT_TYPE_AUTH_PROC_CHECK","ES_EVENT_TYPE_AUTH_GET_TASK","ES_EVENT_TYPE_AUTH_SEARCHFS","ES_EVENT_TYPE_AUTH_FCNTL","ES_EVENT_TYPE_AUTH_IOKIT_OPEN","ES_EVENT_TYPE_AUTH_PROC_SUSPEND_RESUME","ES_EVENT_TYPE_AUTH_REMOUNT","ES_EVENT_TYPE_AUTH_GET_TASK_READ","ES_EVENT_TYPE_AUTH_COPYFILE"],"path":"/System/Library/PrivateFrameworks/SkyLight.framework/Versions/A/Resources/WindowServer","type":"ES_MUTE_PATH_TYPE_LITERAL"}
{"eventCount":39,"events":["ES_EVENT_TYPE_AUTH_OPEN","ES_EVENT_TYPE_AUTH_MMAP","ES_EVENT_TYPE_AUTH_MPROTECT","ES_EVENT_TYPE_AUTH_RENAME","ES_EVENT_TYPE_AUTH_SIGNAL","ES_EVENT_TYPE_AUTH_UNLINK","ES_EVENT_TYPE_AUTH_READLINK","ES_EVENT_TYPE_AUTH_TRUNCATE","ES_EVENT_TYPE_AUTH_LINK","ES_EVENT_TYPE_AUTH_CREATE","ES_EVENT_TYPE_AUTH_SETATTRLIST","ES_EVENT_TYPE_AUTH_SETEXTATTR","ES_EVENT_TYPE_AUTH_SETFLAGS","ES_EVENT_TYPE_AUTH_SETMODE","ES_EVENT_TYPE_AUTH_SETOWNER","ES_EVENT_TYPE_AUTH_CHDIR","ES_EVENT_TYPE_AUTH_GETATTRLIST","ES_EVENT_TYPE_AUTH_CHROOT","ES_EVENT_TYPE_AUTH_UTIMES","ES_EVENT_TYPE_AUTH_CLONE","ES_EVENT_TYPE_AUTH_GETEXTATTR","ES_EVENT_TYPE_AUTH_LISTEXTATTR","ES_EVENT_TYPE_AUTH_READDIR","ES_EVENT_TYPE_AUTH_DELETEEXTATTR","ES_EVENT_TYPE_AUTH_FSGETPATH","ES_EVENT_TYPE_AUTH_SETTIME","ES_EVENT_TYPE_AUTH_UIPC_BIND","ES_EVENT_TYPE_AUTH_UIPC_CONNECT","ES_EVENT_TYPE_AUTH_EXCHANGEDATA","ES_EVENT_TYPE_AUTH_SETACL","ES_EVENT_TYPE_AUTH_PROC_CHECK","ES_EVENT_TYPE_AUTH_GET_TASK","ES_EVENT_TYPE_AUTH_SEARCHFS","ES_EVENT_TYPE_AUTH_FCNTL","ES_EVENT_TYPE_AUTH_IOKIT_OPEN","ES_EVENT_TYPE_AUTH_PROC_SUSPEND_RESUME","ES_EVENT_TYPE_AUTH_REMOUNT","ES_EVENT_TYPE_AUTH_GET_TASK_READ","ES_EVENT_TYPE_AUTH_COPYFILE"],"path":"/usr/sbin/lsof","type":"ES_MUTE_PATH_TYPE_LITERAL"}
{"eventCount":39,"events":["ES_EVENT_TYPE_AUTH_OPEN","ES_EVENT_TYPE_AUTH_MMAP","ES_EVENT_TYPE_AUTH_MPROTECT","ES_EVENT_TYPE_AUTH_RENAME","ES_EVENT_TYPE_AUTH_SIGNAL","ES_EVENT_TYPE_AUTH_UNLINK","ES_EVENT_TYPE_AUTH_READLINK","ES_EVENT_TYPE_AUTH_TRUNCATE","ES_EVENT_TYPE_AUTH_LINK","ES_EVENT_TYPE_AUTH_CREATE","ES_EVENT_TYPE_AUTH_SETATTRLIST","ES_EVENT_TYPE_AUTH_SETEXTATTR","ES_EVENT_TYPE_AUTH_SETFLAGS","ES_EVENT_TYPE_AUTH_SETMODE","ES_EVENT_TYPE_AUTH_SETOWNER","ES_EVENT_TYPE_AUTH_CHDIR","ES_EVENT_TYPE_AUTH_GETATTRLIST","ES_EVENT_TYPE_AUTH_CHROOT","ES_EVENT_TYPE_AUTH_UTIMES","ES_EVENT_TYPE_AUTH_CLONE","ES_EVENT_TYPE_AUTH_GETEXTATTR","ES_EVENT_TYPE_AUTH_LISTEXTATTR","ES_EVENT_TYPE_AUTH_READDIR","ES_EVENT_TYPE_AUTH_DELETEEXTATTR","ES_EVENT_TYPE_AUTH_FSGETPATH","ES_EVENT_TYPE_AUTH_SETTIME","ES_EVENT_TYPE_AUTH_UIPC_BIND","ES_EVENT_TYPE_AUTH_UIPC_CONNECT","ES_EVENT_TYPE_AUTH_EXCHANGEDATA","ES_EVENT_TYPE_AUTH_SETACL","ES_EVENT_TYPE_AUTH_PROC_CHECK","ES_EVENT_TYPE_AUTH_GET_TASK","ES_EVENT_TYPE_AUTH_SEARCHFS","ES_EVENT_TYPE_AUTH_FCNTL","ES_EVENT_TYPE_AUTH_IOKIT_OPEN","ES_EVENT_TYPE_AUTH_PROC_SUSPEND_RESUME","ES_EVENT_TYPE_AUTH_REMOUNT","ES_EVENT_TYPE_AUTH_GET_TASK_READ","ES_EVENT_TYPE_AUTH_COPYFILE"],"path":"/System/Library/Frameworks/SystemExtensions.framework/Versions/A/Helpers/sysextd","type":"ES_MUTE_PATH_TYPE_LITERAL"}
{"eventCount":39,"events":["ES_EVENT_TYPE_AUTH_OPEN","ES_EVENT_TYPE_AUTH_MMAP","ES_EVENT_TYPE_AUTH_MPROTECT","ES_EVENT_TYPE_AUTH_RENAME","ES_EVENT_TYPE_AUTH_SIGNAL","ES_EVENT_TYPE_AUTH_UNLINK","ES_EVENT_TYPE_AUTH_READLINK","ES_EVENT_TYPE_AUTH_TRUNCATE","ES_EVENT_TYPE_AUTH_LINK","ES_EVENT_TYPE_AUTH_CREATE","ES_EVENT_TYPE_AUTH_SETATTRLIST","ES_EVENT_TYPE_AUTH_SETEXTATTR","ES_EVENT_TYPE_AUTH_SETFLAGS","ES_EVENT_TYPE_AUTH_SETMODE","ES_EVENT_TYPE_AUTH_SETOWNER","ES_EVENT_TYPE_AUTH_CHDIR","ES_EVENT_TYPE_AUTH_GETATTRLIST","ES_EVENT_TYPE_AUTH_CHROOT","ES_EVENT_TYPE_AUTH_UTIMES","ES_EVENT_TYPE_AUTH_CLONE","ES_EVENT_TYPE_AUTH_GETEXTATTR","ES_EVENT_TYPE_AUTH_LISTEXTATTR","ES_EVENT_TYPE_AUTH_READDIR","ES_EVENT_TYPE_AUTH_DELETEEXTATTR","ES_EVENT_TYPE_AUTH_FSGETPATH","ES_EVENT_TYPE_AUTH_SETTIME","ES_EVENT_TYPE_AUTH_UIPC_BIND","ES_EVENT_TYPE_AUTH_UIPC_CONNECT","ES_EVENT_TYPE_AUTH_EXCHANGEDATA","ES_EVENT_TYPE_AUTH_SETACL","ES_EVENT_TYPE_AUTH_PROC_CHECK","ES_EVENT_TYPE_AUTH_GET_TASK","ES_EVENT_TYPE_AUTH_SEARCHFS","ES_EVENT_TYPE_AUTH_FCNTL","ES_EVENT_TYPE_AUTH_IOKIT_OPEN","ES_EVENT_TYPE_AUTH_PROC_SUSPEND_RESUME","ES_EVENT_TYPE_AUTH_REMOUNT","ES_EVENT_TYPE_AUTH_GET_TASK_READ","ES_EVENT_TYPE_AUTH_COPYFILE"],"path":"/usr/bin/sample","type":"ES_MUTE_PATH_TYPE_LITERAL"}